{"v":"5.7.6","fr":29.9700012207031,"ip":0,"op":136.000005539394,"w":200,"h":200,"nm":"2 Calendar 2 reversed","ddd":0,"assets":[{"id":"comp_0","layers":[{"ddd":0,"ind":1,"ty":4,"nm":"Profile","sr":1,"ks":{"o":{"a":0,"k":100,"ix":11},"r":{"a":0,"k":0,"ix":10},"p":{"a":0,"k":[100.375,90.75,0],"ix":2,"l":2},"a":{"a":0,"k":[40.125,-27.5,0],"ix":1,"l":2},"s":{"a":0,"k":[181.739,181.739,100],"ix":6,"l":2}},"ao":0,"shapes":[{"ty":"gr","it":[{"d":1,"ty":"el","s":{"a":0,"k":[9.749,9.749],"ix":2},"p":{"a":0,"k":[0,0],"ix":3},"nm":"Ellipse Path 1","mn":"ADBE Vector Shape - Ellipse","hd":false},{"ty":"st","c":{"a":0,"k":[0.12158203125,0.117645263672,0.172546386719,1],"ix":3},"o":{"a":0,"k":100,"ix":4},"w":{"a":0,"k":1.2,"ix":5},"lc":1,"lj":1,"ml":4,"bm":0,"nm":"Stroke 1","mn":"ADBE Vector Graphic - Stroke","hd":false},{"ty":"tr","p":{"a":0,"k":[40.125,-32.25],"ix":2},"a":{"a":0,"k":[0,0],"ix":1},"s":{"a":0,"k":[100,100],"ix":3},"r":{"a":0,"k":0,"ix":6},"o":{"a":0,"k":100,"ix":7},"sk":{"a":0,"k":0,"ix":4},"sa":{"a":0,"k":0,"ix":5},"nm":"Transform"}],"nm":"Ellipse 2","np":3,"cix":2,"bm":0,"ix":1,"mn":"ADBE Vector Group","hd":false},{"ty":"gr","it":[{"ind":0,"ty":"sh","ix":1,"ks":{"a":0,"k":{"i":[[0.375,0.25],[-9.75,0],[0,0]],"o":[[-0.375,-0.25],[7.75,0],[0,0]],"v":[[31.25,-16.5],[40.25,-25.625],[49.125,-16.625]],"c":false},"ix":2},"nm":"Path 1","mn":"ADBE Vector Shape - Group","hd":false},{"ty":"st","c":{"a":0,"k":[0.12158203125,0.117645263672,0.172546386719,1],"ix":3},"o":{"a":0,"k":100,"ix":4},"w":{"a":0,"k":1.2,"ix":5},"lc":1,"lj":1,"ml":4,"bm":0,"nm":"Stroke 1","mn":"ADBE Vector Graphic - Stroke","hd":false},{"ty":"tr","p":{"a":0,"k":[0,0],"ix":2},"a":{"a":0,"k":[0,0],"ix":1},"s":{"a":0,"k":[100,100],"ix":3},"r":{"a":0,"k":0,"ix":6},"o":{"a":0,"k":100,"ix":7},"sk":{"a":0,"k":0,"ix":4},"sa":{"a":0,"k":0,"ix":5},"nm":"Transform"}],"nm":"Shape 1","np":3,"cix":2,"bm":0,"ix":2,"mn":"ADBE Vector Group","hd":false},{"ty":"gr","it":[{"d":1,"ty":"el","s":{"a":0,"k":[28.75,28.75],"ix":2},"p":{"a":0,"k":[0,0],"ix":3},"nm":"Ellipse Path 1","mn":"ADBE Vector Shape - Ellipse","hd":false},{"ty":"st","c":{"a":0,"k":[0.12158203125,0.117645263672,0.172546386719,1],"ix":3},"o":{"a":0,"k":100,"ix":4},"w":{"a":0,"k":1.2,"ix":5},"lc":1,"lj":1,"ml":4,"bm":0,"nm":"Stroke 1","mn":"ADBE Vector Graphic - Stroke","hd":false},{"ty":"tr","p":{"a":0,"k":[40.125,-27.5],"ix":2},"a":{"a":0,"k":[0,0],"ix":1},"s":{"a":0,"k":[100,100],"ix":3},"r":{"a":0,"k":0,"ix":6},"o":{"a":0,"k":100,"ix":7},"sk":{"a":0,"k":0,"ix":4},"sa":{"a":0,"k":0,"ix":5},"nm":"Transform"}],"nm":"Ellipse 1","np":3,"cix":2,"bm":0,"ix":3,"mn":"ADBE Vector Group","hd":false}],"ip":0,"op":150.000006109625,"st":0,"bm":0},{"ddd":0,"ind":3,"ty":4,"nm":"hang up","sr":1,"ks":{"o":{"a":0,"k":100,"ix":11},"r":{"a":0,"k":0,"ix":10},"p":{"a":0,"k":[73.062,136.625,0],"ix":2,"l":2},"a":{"a":0,"k":[-20.062,40.25,0],"ix":1,"l":2},"s":{"a":0,"k":[80.822,80.822,100],"ix":6,"l":2}},"ao":0,"shapes":[{"ty":"gr","it":[{"ind":0,"ty":"sh","ix":1,"ks":{"a":0,"k":{"i":[[0,0],[0,0],[0,0],[0,0],[0,0],[0,0],[0,0]],"o":[[0,0],[0,0],[0,0],[0,0],[0,0],[0,0],[0,0]],"v":[[-17.75,39.25],[-22.125,39.25],[-22.125,43.75],[-25.812,43.75],[-20.125,49.375],[-14.188,43.812],[-17.75,43.812]],"c":true},"ix":2},"nm":"Path 1","mn":"ADBE Vector Shape - Group","hd":false},{"ty":"st","c":{"a":0,"k":[0.12158203125,0.117645263672,0.172546386719,1],"ix":3},"o":{"a":0,"k":100,"ix":4},"w":{"a":0,"k":1.2,"ix":5},"lc":1,"lj":1,"ml":4,"bm":0,"nm":"Stroke 1","mn":"ADBE Vector Graphic - Stroke","hd":false},{"ty":"tr","p":{"a":0,"k":[0,0],"ix":2},"a":{"a":0,"k":[0,0],"ix":1},"s":{"a":0,"k":[100,100],"ix":3},"r":{"a":0,"k":0,"ix":6},"o":{"a":0,"k":100,"ix":7},"sk":{"a":0,"k":0,"ix":4},"sa":{"a":0,"k":0,"ix":5},"nm":"Transform"}],"nm":"Shape 2","np":3,"cix":2,"bm":0,"ix":1,"mn":"ADBE Vector Group","hd":false},{"ty":"gr","it":[{"ty":"tr","p":{"a":0,"k":[0,0],"ix":2},"a":{"a":0,"k":[0,0],"ix":1},"s":{"a":0,"k":[100,100],"ix":3},"r":{"a":0,"k":0,"ix":6},"o":{"a":0,"k":100,"ix":7},"sk":{"a":0,"k":0,"ix":4},"sa":{"a":0,"k":0,"ix":5},"nm":"Transform"}],"nm":"Shape 1","np":0,"cix":2,"bm":0,"ix":2,"mn":"ADBE Vector Group","hd":false},{"ty":"gr","it":[{"ind":0,"ty":"sh","ix":1,"ks":{"a":0,"k":{"i":[[-3.75,0],[-1.625,-0.375],[0.75,-1.125],[0.688,0.582],[0.75,1.031],[0,0]],"o":[[3.75,0],[1.625,0.375],[-0.75,1.125],[-1.625,-1.375],[-1,-1.375],[0,0]],"v":[[-20.125,31.125],[-7.75,32.688],[-6,39.875],[-14,40.625],[-13.75,35.75],[-20.125,34.125]],"c":false},"ix":2},"nm":"Path 1","mn":"ADBE Vector Shape - Group","hd":false},{"ind":1,"ty":"sh","ix":2,"ks":{"a":0,"k":{"i":[[3.75,0],[1.625,-0.375],[-0.75,-1.125],[-0.688,0.582],[-0.75,1.031],[0,0]],"o":[[-3.75,0],[-1.625,0.375],[0.75,1.125],[1.625,-1.375],[1,-1.375],[0,0]],"v":[[-20,31.125],[-32.375,32.688],[-34.125,39.875],[-26.125,40.625],[-26.562,35.75],[-20,34.125]],"c":false},"ix":2},"nm":"Path 2","mn":"ADBE Vector Shape - Group","hd":false},{"ty":"st","c":{"a":0,"k":[0.12158203125,0.117645263672,0.172546386719,1],"ix":3},"o":{"a":0,"k":100,"ix":4},"w":{"a":0,"k":1.2,"ix":5},"lc":1,"lj":1,"ml":4,"bm":0,"nm":"Stroke 1","mn":"ADBE Vector Graphic - Stroke","hd":false},{"ty":"tr","p":{"a":0,"k":[0,0],"ix":2},"a":{"a":0,"k":[0,0],"ix":1},"s":{"a":0,"k":[100,100],"ix":3},"r":{"a":0,"k":0,"ix":6},"o":{"a":0,"k":100,"ix":7},"sk":{"a":0,"k":0,"ix":4},"sa":{"a":0,"k":0,"ix":5},"nm":"Transform"}],"nm":"Group 1","np":3,"cix":2,"bm":0,"ix":3,"mn":"ADBE Vector Group","hd":false}],"ip":0,"op":150.000006109625,"st":0,"bm":0},{"ddd":0,"ind":4,"ty":4,"nm":"Mute","sr":1,"ks":{"o":{"a":0,"k":100,"ix":11},"r":{"a":0,"k":0,"ix":10},"p":{"a":0,"k":[47.875,126.687,0],"ix":2,"l":2},"a":{"a":0,"k":[-52.125,31.688,0],"ix":1,"l":2},"s":{"a":0,"k":[82.319,82.319,100],"ix":6,"l":2}},"ao":0,"shapes":[{"ty":"gr","it":[{"ind":0,"ty":"sh","ix":1,"ks":{"a":0,"k":{"i":[[0,0],[0,0]],"o":[[0,0],[0,0]],"v":[[-57,51.125],[-47.125,51.125]],"c":false},"ix":2},"nm":"Path 1","mn":"ADBE Vector Shape - Group","hd":false},{"ty":"st","c":{"a":0,"k":[0.12158203125,0.117645263672,0.172546386719,1],"ix":3},"o":{"a":0,"k":100,"ix":4},"w":{"a":0,"k":1.2,"ix":5},"lc":1,"lj":1,"ml":4,"bm":0,"nm":"Stroke 1","mn":"ADBE Vector Graphic - Stroke","hd":false},{"ty":"tr","p":{"a":0,"k":[0,0],"ix":2},"a":{"a":0,"k":[0,0],"ix":1},"s":{"a":0,"k":[100,100],"ix":3},"r":{"a":0,"k":0,"ix":6},"o":{"a":0,"k":100,"ix":7},"sk":{"a":0,"k":0,"ix":4},"sa":{"a":0,"k":0,"ix":5},"nm":"Transform"}],"nm":"Shape 2","np":3,"cix":2,"bm":0,"ix":1,"mn":"ADBE Vector Group","hd":false},{"ty":"gr","it":[{"ind":0,"ty":"sh","ix":1,"ks":{"a":0,"k":{"i":[[0,0],[0,0]],"o":[[0,0],[0,0]],"v":[[-52,51.188],[-52,45]],"c":false},"ix":2},"nm":"Path 1","mn":"ADBE Vector Shape - Group","hd":false},{"ty":"st","c":{"a":0,"k":[0.12158203125,0.117645263672,0.172546386719,1],"ix":3},"o":{"a":0,"k":100,"ix":4},"w":{"a":0,"k":1.2,"ix":5},"lc":1,"lj":1,"ml":4,"bm":0,"nm":"Stroke 1","mn":"ADBE Vector Graphic - Stroke","hd":false},{"ty":"tr","p":{"a":0,"k":[0,0],"ix":2},"a":{"a":0,"k":[0,0],"ix":1},"s":{"a":0,"k":[100,100],"ix":3},"r":{"a":0,"k":0,"ix":6},"o":{"a":0,"k":100,"ix":7},"sk":{"a":0,"k":0,"ix":4},"sa":{"a":0,"k":0,"ix":5},"nm":"Transform"}],"nm":"Shape 1","np":3,"cix":2,"bm":0,"ix":2,"mn":"ADBE Vector Group","hd":false},{"ty":"gr","it":[{"ty":"gr","it":[{"ind":0,"ty":"sh","ix":1,"ks":{"a":0,"k":{"i":[[0,-2.14],[0,0],[-1.06,-0.056],[1.341,0],[0.409,4.083],[-0.719,0.117],[0,0],[-2.14,0]],"o":[[0,0],[0.636,0.079],[-0.377,4.12],[-1.227,0],[0.675,-0.131],[0,0],[0,-2.14],[2.14,0]],"v":[[3.875,-3.844],[3.881,8.121],[5.805,8.255],[0.003,13.287],[-5.724,8.331],[-3.875,8.159],[-3.875,-3.844],[0,-7.719]],"c":true},"ix":2},"nm":"Path 1","mn":"ADBE Vector Shape - Group","hd":false},{"ty":"tr","p":{"a":0,"k":[-52.125,31.688],"ix":2},"a":{"a":0,"k":[0,0],"ix":1},"s":{"a":0,"k":[100,100],"ix":3},"r":{"a":0,"k":0,"ix":6},"o":{"a":0,"k":100,"ix":7},"sk":{"a":0,"k":0,"ix":4},"sa":{"a":0,"k":0,"ix":5},"nm":"Transform"}],"nm":"Rectangle 2","np":1,"cix":2,"bm":0,"ix":1,"mn":"ADBE Vector Group","hd":false},{"ty":"st","c":{"a":0,"k":[0.12158203125,0.117645263672,0.172546386719,1],"ix":3},"o":{"a":0,"k":100,"ix":4},"w":{"a":0,"k":1.2,"ix":5},"lc":1,"lj":1,"ml":4,"bm":0,"nm":"Stroke 1","mn":"ADBE Vector Graphic - Stroke","hd":false},{"ty":"tr","p":{"a":0,"k":[-52.125,34.453],"ix":2},"a":{"a":0,"k":[-52.125,34.453],"ix":1},"s":{"a":0,"k":[100,100],"ix":3},"r":{"a":0,"k":0,"ix":6},"o":{"a":0,"k":100,"ix":7},"sk":{"a":0,"k":0,"ix":4},"sa":{"a":0,"k":0,"ix":5},"nm":"Transform"}],"nm":"Mic","np":2,"cix":2,"bm":0,"ix":3,"mn":"ADBE Vector Group","hd":false}],"ip":0,"op":150.000006109625,"st":0,"bm":0}]}],"layers":[{"ddd":0,"ind":1,"ty":0,"nm":"Video call reversed Pre","refId":"comp_0","sr":1,"ks":{"o":{"a":0,"k":100,"ix":11},"r":{"a":0,"k":0,"ix":10},"p":{"a":0,"k":[98,113.75,0],"ix":2,"l":2},"a":{"a":0,"k":[100,113.75,0],"ix":1,"l":2},"s":{"a":1,"k":[{"i":{"x":[0.34,0.34,0.667],"y":[1,1,1]},"o":{"x":[0.333,0.333,0.333],"y":[0,0,0]},"t":38,"s":[1.538,1.538,100]},{"i":{"x":[0.667,0.667,0.667],"y":[1,1,1]},"o":{"x":[0.333,0.333,0.333],"y":[0,0,0]},"t":51,"s":[100,100,100]},{"i":{"x":[0.667,0.667,0.667],"y":[1,1,1]},"o":{"x":[0.66,0.66,0.333],"y":[0,0,0]},"t":88,"s":[100,100,100]},{"t":100.000004073084,"s":[1.538,1.538,100]}],"ix":6,"l":2}},"ao":0,"w":200,"h":200,"ip":38.0000015477717,"op":100.000004073084,"st":0,"bm":0},{"ddd":0,"ind":2,"ty":4,"nm":"Day","sr":1,"ks":{"o":{"a":0,"k":100,"ix":11},"r":{"a":0,"k":0,"ix":10},"p":{"a":0,"k":[100,114.245,0],"ix":2,"l":2},"a":{"a":0,"k":[-1664.902,-185.255,0],"ix":1,"l":2},"s":{"a":0,"k":[34.542,34.542,100],"ix":6,"l":2}},"ao":0,"shapes":[{"ty":"gr","it":[{"ind":0,"ty":"sh","ix":1,"ks":{"a":1,"k":[{"i":{"x":0.833,"y":0.833},"o":{"x":0.167,"y":0},"t":34,"s":[{"i":[[-2.649,0.747],[-1.787,0.651],[-0.18,6.747],[0.27,1.349],[2.609,-0.18],[7.208,-5.026],[1.234,-4.795],[-0.825,-1.083],[-1.799,-0.09],[-7.691,-0.551],[-0.851,-1.075]],"o":[[0.08,-0.93],[1.787,-0.651],[0.18,-6.747],[-0.27,-1.349],[-2.609,0.18],[-4.892,3.411],[-3.286,12.773],[2.215,2.906],[1.799,0.09],[7.691,0.551],[0.851,1.075]],"v":[[-1653.12,-165.118],[-1655.273,-168.287],[-1645.606,-175.586],[-1648.413,-196.932],[-1653.65,-204.063],[-1679.89,-204.461],[-1687.851,-197.833],[-1688.467,-173.129],[-1676.988,-167.225],[-1660.894,-165.678],[-1653.573,-165.372]],"c":false}]},{"i":{"x":0.667,"y":1},"o":{"x":0.167,"y":0.167},"t":36,"s":[{"i":[[-2.016,0.568],[-1.359,0.496],[-0.137,5.133],[0.205,1.027],[1.985,-0.137],[-4.245,0],[-0.137,-3.764],[0.137,-1.027],[-1.369,-0.068],[-0.821,0],[-1.506,-0.89]],"o":[[0.061,-0.708],[1.359,-0.496],[0.137,-5.133],[-0.205,-1.027],[-1.985,0.137],[6.173,0],[0.137,3.764],[-0.137,1.027],[1.369,0.068],[0.821,0],[1.506,0.89]],"v":[[-1657.114,-172.123],[-1657.926,-172.469],[-1650.021,-178.16],[-1650.367,-193.574],[-1656.691,-199.688],[-1676.656,-199.991],[-1682.713,-194.948],[-1682.218,-176.429],[-1677.751,-172.763],[-1660.964,-172.136],[-1656.771,-172.454]],"c":false}]},{"i":{"x":0.833,"y":0.833},"o":{"x":0.66,"y":0},"t":38,"s":[{"i":[[-2.649,0.747],[-1.787,0.651],[-0.18,6.747],[0.27,1.349],[2.609,-0.18],[-5.58,0],[-0.18,-4.948],[0.18,-1.349],[-1.799,-0.09],[-1.079,0],[-1.979,-1.169]],"o":[[0.08,-0.93],[1.787,-0.651],[0.18,-6.747],[-0.27,-1.349],[-2.609,0.18],[8.113,0],[0.18,4.948],[-0.18,1.349],[1.799,0.09],[1.079,0],[1.979,1.169]],"v":[[-1654.205,-167.832],[-1655.273,-168.287],[-1644.882,-175.767],[-1645.337,-196.027],[-1653.65,-204.063],[-1679.89,-204.461],[-1687.851,-197.833],[-1687.201,-173.491],[-1681.33,-168.673],[-1659.266,-167.849],[-1653.754,-168.267]],"c":false}]},{"i":{"x":0,"y":0},"o":{"x":0.167,"y":0.167},"t":46,"s":[{"i":[[-4.711,1.893],[-16.15,6.722],[-1.348,50.559],[14.697,38.796],[19.55,-1.348],[82.614,-16.677],[-0.014,-27.404],[-11.993,-36.128],[-12.089,-5.981],[-8.089,0],[-14.831,-8.764]],"o":[[6.307,-2.639],[16.15,-6.722],[1.348,-50.559],[-3.64,-9.647],[-19.55,1.348],[-23.399,4.826],[0.014,37.101],[3.178,9.682],[14.817,7.345],[8.089,0],[14.831,8.764]],"v":[[-1556.831,-48.461],[-1517.391,-84.519],[-1481.222,-117.125],[-1481.925,-330.174],[-1510.593,-354.151],[-1788.484,-355.516],[-1857.483,-323.645],[-1849.427,-118.948],[-1833.625,-82.548],[-1619.766,-81.149],[-1573.306,-71.843]],"c":false}]},{"i":{"x":0.833,"y":0.833},"o":{"x":0.324,"y":0.324},"t":51,"s":[{"i":[[-4.886,1.99],[-17.37,7.238],[-1.448,54.281],[15.922,41.978],[20.989,-1.447],[90.107,-18.094],[0,-29.312],[-13.027,-39.083],[-12.963,-6.481],[-8.685,0],[-15.922,-9.409]],"o":[[6.836,-2.784],[17.37,-7.238],[1.448,-54.281],[-3.927,-10.352],[-20.989,1.447],[-26.077,5.236],[0,39.833],[3.463,10.39],[15.923,7.961],[8.685,0],[15.922,9.409]],"v":[[-1548.558,-38.319],[-1505.676,-77.402],[-1467.318,-112.142],[-1468.041,-341.572],[-1498.439,-366.903],[-1797.71,-368.35],[-1871.895,-334.334],[-1863.21,-114.313],[-1846.564,-75.231],[-1616.41,-73.783],[-1566.471,-63.651]],"c":false}]},{"i":{"x":0.833,"y":0.833},"o":{"x":1,"y":1},"t":88,"s":[{"i":[[-4.886,1.99],[-17.37,7.238],[-1.448,54.281],[15.922,41.978],[20.989,-1.447],[90.107,-18.094],[0,-29.312],[-13.027,-39.083],[-12.963,-6.481],[-8.685,0],[-15.922,-9.409]],"o":[[6.836,-2.784],[17.37,-7.238],[1.448,-54.281],[-3.927,-10.352],[-20.989,1.447],[-26.077,5.236],[0,39.833],[3.463,10.39],[15.923,7.961],[8.685,0],[15.922,9.409]],"v":[[-1548.558,-38.319],[-1505.676,-77.402],[-1467.318,-112.142],[-1468.041,-341.572],[-1498.439,-366.903],[-1797.71,-368.35],[-1871.895,-334.334],[-1863.21,-114.313],[-1846.564,-75.231],[-1616.41,-73.783],[-1566.471,-63.651]],"c":false}]},{"i":{"x":0.34,"y":1},"o":{"x":0.167,"y":0.167},"t":92,"s":[{"i":[[-4.696,1.885],[-16.046,6.678],[-1.34,50.242],[14.593,38.525],[19.427,-1.34],[83.063,-16.983],[0.105,-27.229],[-11.991,-35.854],[-12.015,-5.938],[-8.6,-0.047],[-14.642,-8.701]],"o":[[6.261,-2.627],[16.046,-6.678],[1.34,-50.243],[-3.616,-9.587],[-19.427,1.34],[-24.276,5.081],[-0.279,37.533],[3.357,9.754],[14.723,7.292],[8.601,0.047],[14.642,8.701]],"v":[[-1557.442,-49.093],[-1518.387,-85.124],[-1482.466,-117.533],[-1483.367,-329.282],[-1511.627,-353.067],[-1787.699,-354.425],[-1856.257,-322.736],[-1848.362,-119.311],[-1832.155,-83.047],[-1620.19,-81.591],[-1573.872,-72.294]],"c":false}]},{"t":100.000004073084,"s":[{"i":[[-2.649,0.747],[-1.787,0.651],[-0.18,6.747],[0.27,1.349],[2.609,-0.18],[7.208,-5.026],[1.234,-4.795],[-0.825,-1.083],[-1.799,-0.09],[-7.691,-0.551],[-0.851,-1.075]],"o":[[0.08,-0.93],[1.787,-0.651],[0.18,-6.747],[-0.27,-1.349],[-2.609,0.18],[-4.892,3.411],[-3.286,12.773],[2.215,2.906],[1.799,0.09],[7.691,0.551],[0.851,1.075]],"v":[[-1653.12,-165.118],[-1655.273,-168.287],[-1645.606,-175.586],[-1648.413,-196.932],[-1653.65,-204.063],[-1679.89,-204.461],[-1687.851,-197.833],[-1688.467,-173.129],[-1676.988,-167.225],[-1660.894,-165.678],[-1653.573,-165.372]],"c":false}]}],"ix":2},"nm":"Path 1","mn":"ADBE Vector Shape - Group","hd":false},{"ty":"st","c":{"a":0,"k":[0.12158203125,0.117645263672,0.172546386719,1],"ix":3},"o":{"a":0,"k":100,"ix":4},"w":{"a":1,"k":[{"i":{"x":[0.667],"y":[1]},"o":{"x":[0.333],"y":[0]},"t":38,"s":[5]},{"i":{"x":[0.667],"y":[1]},"o":{"x":[0.333],"y":[0]},"t":51,"s":[7]},{"i":{"x":[0.667],"y":[1]},"o":{"x":[0.333],"y":[0]},"t":88,"s":[7]},{"t":100.000004073084,"s":[5]}],"ix":5},"lc":1,"lj":1,"ml":4,"bm":0,"nm":"Stroke 2","mn":"ADBE Vector Graphic - Stroke","hd":false},{"ty":"tr","p":{"a":0,"k":[-1669.706,-211.808],"ix":2},"a":{"a":0,"k":[-1669.706,-211.808],"ix":1},"s":{"a":0,"k":[100,100],"ix":3},"r":{"a":0,"k":0,"ix":6},"o":{"a":0,"k":100,"ix":7},"sk":{"a":0,"k":0,"ix":4},"sa":{"a":0,"k":0,"ix":5},"nm":"Transform"}],"nm":"Group 1","np":3,"cix":2,"bm":0,"ix":1,"mn":"ADBE Vector Group","hd":false}],"ip":0,"op":136.000005539394,"st":0,"bm":0},{"ddd":0,"ind":3,"ty":4,"nm":"Matte","td":1,"sr":1,"ks":{"o":{"a":0,"k":100,"ix":11},"r":{"a":0,"k":0,"ix":10},"p":{"a":0,"k":[100,114.245,0],"ix":2,"l":2},"a":{"a":0,"k":[-1664.902,-185.255,0],"ix":1,"l":2},"s":{"a":0,"k":[34.542,34.542,100],"ix":6,"l":2}},"ao":0,"shapes":[{"ty":"gr","it":[{"ind":0,"ty":"sh","ix":1,"ks":{"a":1,"k":[{"i":{"x":0.833,"y":0.833},"o":{"x":0.167,"y":0},"t":34,"s":[{"i":[[-2.649,0.747],[-1.787,0.651],[-0.18,6.747],[0.27,1.349],[2.609,-0.18],[7.208,-5.026],[1.234,-4.795],[-0.825,-1.083],[-1.799,-0.09],[-7.691,-0.551],[-0.851,-1.075]],"o":[[0.08,-0.93],[1.787,-0.651],[0.18,-6.747],[-0.27,-1.349],[-2.609,0.18],[-4.892,3.411],[-3.286,12.773],[2.215,2.906],[1.799,0.09],[7.691,0.551],[0.851,1.075]],"v":[[-1653.12,-165.118],[-1655.273,-168.287],[-1645.606,-175.586],[-1648.413,-196.932],[-1653.65,-204.063],[-1679.89,-204.461],[-1687.851,-197.833],[-1688.467,-173.129],[-1676.988,-167.225],[-1660.894,-165.678],[-1653.573,-165.372]],"c":false}]},{"i":{"x":0.667,"y":1},"o":{"x":0.167,"y":0.167},"t":36,"s":[{"i":[[-2.016,0.568],[-1.359,0.496],[-0.137,5.133],[0.205,1.027],[1.985,-0.137],[-4.245,0],[-0.137,-3.764],[0.137,-1.027],[-1.369,-0.068],[-0.821,0],[-1.506,-0.89]],"o":[[0.061,-0.708],[1.359,-0.496],[0.137,-5.133],[-0.205,-1.027],[-1.985,0.137],[6.173,0],[0.137,3.764],[-0.137,1.027],[1.369,0.068],[0.821,0],[1.506,0.89]],"v":[[-1657.114,-172.123],[-1657.926,-172.469],[-1650.021,-178.16],[-1650.367,-193.574],[-1656.691,-199.688],[-1676.656,-199.991],[-1682.713,-194.948],[-1682.218,-176.429],[-1677.751,-172.763],[-1660.964,-172.136],[-1656.771,-172.454]],"c":false}]},{"i":{"x":0.833,"y":0.833},"o":{"x":0.66,"y":0},"t":38,"s":[{"i":[[-2.649,0.747],[-1.787,0.651],[-0.18,6.747],[0.27,1.349],[2.609,-0.18],[-5.58,0],[-0.18,-4.948],[0.18,-1.349],[-1.799,-0.09],[-1.079,0],[-1.979,-1.169]],"o":[[0.08,-0.93],[1.787,-0.651],[0.18,-6.747],[-0.27,-1.349],[-2.609,0.18],[8.113,0],[0.18,4.948],[-0.18,1.349],[1.799,0.09],[1.079,0],[1.979,1.169]],"v":[[-1654.205,-167.832],[-1655.273,-168.287],[-1644.882,-175.767],[-1645.337,-196.027],[-1653.65,-204.063],[-1679.89,-204.461],[-1687.851,-197.833],[-1687.201,-173.491],[-1681.33,-168.673],[-1659.266,-167.849],[-1653.754,-168.267]],"c":false}]},{"i":{"x":0,"y":0},"o":{"x":0.167,"y":0.167},"t":46,"s":[{"i":[[-4.711,1.893],[-16.15,6.722],[-1.348,50.559],[14.697,38.796],[19.55,-1.348],[82.614,-16.677],[-0.014,-27.404],[-11.993,-36.128],[-12.089,-5.981],[-8.089,0],[-14.831,-8.764]],"o":[[6.307,-2.639],[16.15,-6.722],[1.348,-50.559],[-3.64,-9.647],[-19.55,1.348],[-23.399,4.826],[0.014,37.101],[3.178,9.682],[14.817,7.345],[8.089,0],[14.831,8.764]],"v":[[-1556.831,-48.461],[-1517.391,-84.519],[-1481.222,-117.125],[-1481.925,-330.174],[-1510.593,-354.151],[-1788.484,-355.516],[-1857.483,-323.645],[-1849.427,-118.948],[-1833.625,-82.548],[-1619.766,-81.149],[-1573.306,-71.843]],"c":false}]},{"i":{"x":0.833,"y":0.833},"o":{"x":0.324,"y":0.324},"t":51,"s":[{"i":[[-4.886,1.99],[-17.37,7.238],[-1.448,54.281],[15.922,41.978],[20.989,-1.447],[90.107,-18.094],[0,-29.312],[-13.027,-39.083],[-12.963,-6.481],[-8.685,0],[-15.922,-9.409]],"o":[[6.836,-2.784],[17.37,-7.238],[1.448,-54.281],[-3.927,-10.352],[-20.989,1.447],[-26.077,5.236],[0,39.833],[3.463,10.39],[15.923,7.961],[8.685,0],[15.922,9.409]],"v":[[-1548.558,-38.319],[-1505.676,-77.402],[-1467.318,-112.142],[-1468.041,-341.572],[-1498.439,-366.903],[-1797.71,-368.35],[-1871.895,-334.334],[-1863.21,-114.313],[-1846.564,-75.231],[-1616.41,-73.783],[-1566.471,-63.651]],"c":false}]},{"i":{"x":0.833,"y":0.833},"o":{"x":1,"y":1},"t":88,"s":[{"i":[[-4.886,1.99],[-17.37,7.238],[-1.448,54.281],[15.922,41.978],[20.989,-1.447],[90.107,-18.094],[0,-29.312],[-13.027,-39.083],[-12.963,-6.481],[-8.685,0],[-15.922,-9.409]],"o":[[6.836,-2.784],[17.37,-7.238],[1.448,-54.281],[-3.927,-10.352],[-20.989,1.447],[-26.077,5.236],[0,39.833],[3.463,10.39],[15.923,7.961],[8.685,0],[15.922,9.409]],"v":[[-1548.558,-38.319],[-1505.676,-77.402],[-1467.318,-112.142],[-1468.041,-341.572],[-1498.439,-366.903],[-1797.71,-368.35],[-1871.895,-334.334],[-1863.21,-114.313],[-1846.564,-75.231],[-1616.41,-73.783],[-1566.471,-63.651]],"c":false}]},{"i":{"x":0.34,"y":1},"o":{"x":0.167,"y":0.167},"t":92,"s":[{"i":[[-4.696,1.885],[-16.046,6.678],[-1.34,50.242],[14.593,38.525],[19.427,-1.34],[83.063,-16.983],[0.105,-27.229],[-11.991,-35.854],[-12.015,-5.938],[-8.6,-0.047],[-14.642,-8.701]],"o":[[6.261,-2.627],[16.046,-6.678],[1.34,-50.242],[-3.616,-9.587],[-19.427,1.34],[-24.276,5.081],[-0.279,37.533],[3.357,9.754],[14.723,7.292],[8.601,0.047],[14.642,8.701]],"v":[[-1557.442,-49.093],[-1518.387,-85.124],[-1482.466,-117.533],[-1483.367,-329.282],[-1511.627,-353.067],[-1787.699,-354.425],[-1856.257,-322.736],[-1848.362,-119.311],[-1832.155,-83.047],[-1620.19,-81.591],[-1573.872,-72.294]],"c":false}]},{"t":100.000004073084,"s":[{"i":[[-2.649,0.747],[-1.787,0.651],[-0.18,6.747],[0.27,1.349],[2.609,-0.18],[7.208,-5.026],[1.234,-4.795],[-0.825,-1.083],[-1.799,-0.09],[-7.691,-0.551],[-0.851,-1.075]],"o":[[0.08,-0.93],[1.787,-0.651],[0.18,-6.747],[-0.27,-1.349],[-2.609,0.18],[-4.892,3.411],[-3.286,12.773],[2.215,2.906],[1.799,0.09],[7.691,0.551],[0.851,1.075]],"v":[[-1653.12,-165.118],[-1655.273,-168.287],[-1645.606,-175.586],[-1648.413,-196.932],[-1653.65,-204.063],[-1679.89,-204.461],[-1687.851,-197.833],[-1688.467,-173.129],[-1676.988,-167.225],[-1660.894,-165.678],[-1653.573,-165.372]],"c":false}]}],"ix":2},"nm":"Path 1","mn":"ADBE Vector Shape - Group","hd":false},{"ty":"fl","c":{"a":0,"k":[0.12158203125,0.117645263672,0.172546386719,1],"ix":4},"o":{"a":0,"k":100,"ix":5},"r":1,"bm":0,"nm":"Fill 2","mn":"ADBE Vector Graphic - Fill","hd":false},{"ty":"st","c":{"a":0,"k":[0.956862745098,0.933333333333,0.929411764706,1],"ix":3},"o":{"a":0,"k":100,"ix":4},"w":{"a":1,"k":[{"i":{"x":[0.667],"y":[1]},"o":{"x":[0.333],"y":[0]},"t":38,"s":[10]},{"i":{"x":[0.667],"y":[1]},"o":{"x":[0.333],"y":[0]},"t":51,"s":[11]},{"i":{"x":[0.667],"y":[1]},"o":{"x":[0.333],"y":[0]},"t":88,"s":[11]},{"t":100.000004073084,"s":[10]}],"ix":5},"lc":1,"lj":1,"ml":4,"bm":0,"nm":"Stroke 2","mn":"ADBE Vector Graphic - Stroke","hd":false},{"ty":"tr","p":{"a":0,"k":[-1669.706,-211.808],"ix":2},"a":{"a":0,"k":[-1669.706,-211.808],"ix":1},"s":{"a":0,"k":[100,100],"ix":3},"r":{"a":0,"k":0,"ix":6},"o":{"a":0,"k":100,"ix":7},"sk":{"a":0,"k":0,"ix":4},"sa":{"a":0,"k":0,"ix":5},"nm":"Transform"}],"nm":"Group 1","np":3,"cix":2,"bm":0,"ix":1,"mn":"ADBE Vector Group","hd":false}],"ip":0,"op":136.000005539394,"st":0,"bm":0},{"ddd":0,"ind":4,"ty":4,"nm":"Calendar","tt":2,"sr":1,"ks":{"o":{"a":0,"k":100,"ix":11},"r":{"a":0,"k":0,"ix":10},"p":{"a":0,"k":[99.098,94.4,0],"ix":2,"l":2},"a":{"a":0,"k":[-1664.902,-242.35,0],"ix":1,"l":2},"s":{"a":1,"k":[{"i":{"x":[0.667,0.667,0.667],"y":[1,1,1]},"o":{"x":[0.333,0.333,0.333],"y":[0,0,0]},"t":38,"s":[34.821,34.821,100]},{"i":{"x":[0.667,0.667,0.667],"y":[1,1,1]},"o":{"x":[0.333,0.333,0.333],"y":[0,0,0]},"t":50,"s":[23.897,23.897,100]},{"i":{"x":[0.12,0.12,0.667],"y":[1,1,1]},"o":{"x":[0.333,0.333,0.333],"y":[0,0,0]},"t":88,"s":[23.897,23.897,100]},{"t":100.000004073084,"s":[34.821,34.821,100]}],"ix":6,"l":2}},"ao":0,"shapes":[{"ty":"gr","it":[{"ty":"rc","d":1,"s":{"a":0,"k":[41.63,41.63],"ix":2},"p":{"a":0,"k":[-1526.829,-118.189],"ix":3},"r":{"a":0,"k":0,"ix":4},"nm":"Rectangle Path 1","mn":"ADBE Vector Shape - Rect","hd":false},{"ty":"tr","p":{"a":0,"k":[0,0],"ix":2},"a":{"a":0,"k":[0,0],"ix":1},"s":{"a":0,"k":[100,100],"ix":3},"r":{"a":0,"k":0,"ix":6},"o":{"a":0,"k":100,"ix":7},"sk":{"a":0,"k":0,"ix":4},"sa":{"a":0,"k":0,"ix":5},"nm":"Transform"}],"nm":"Group 3","np":1,"cix":2,"bm":0,"ix":1,"mn":"ADBE Vector Group","hd":false},{"ty":"gr","it":[{"ty":"rc","d":1,"s":{"a":0,"k":[41.63,41.63],"ix":2},"p":{"a":0,"k":[-1526.829,-185.255],"ix":3},"r":{"a":0,"k":0,"ix":4},"nm":"Rectangle Path 1","mn":"ADBE Vector Shape - Rect","hd":false},{"ty":"tr","p":{"a":0,"k":[0,0],"ix":2},"a":{"a":0,"k":[0,0],"ix":1},"s":{"a":0,"k":[100,100],"ix":3},"r":{"a":0,"k":0,"ix":6},"o":{"a":0,"k":100,"ix":7},"sk":{"a":0,"k":0,"ix":4},"sa":{"a":0,"k":0,"ix":5},"nm":"Transform"}],"nm":"Group 4","np":1,"cix":2,"bm":0,"ix":2,"mn":"ADBE Vector Group","hd":false},{"ty":"gr","it":[{"ty":"rc","d":3,"s":{"a":0,"k":[41.63,41.63],"ix":2},"p":{"a":0,"k":[-1526.829,-252.321],"ix":3},"r":{"a":0,"k":0,"ix":4},"nm":"Rectangle Path 1","mn":"ADBE Vector Shape - Rect","hd":false},{"ty":"tr","p":{"a":0,"k":[0,0],"ix":2},"a":{"a":0,"k":[0,0],"ix":1},"s":{"a":0,"k":[100,100],"ix":3},"r":{"a":0,"k":0,"ix":6},"o":{"a":0,"k":100,"ix":7},"sk":{"a":0,"k":0,"ix":4},"sa":{"a":0,"k":0,"ix":5},"nm":"Transform"}],"nm":"Group 5","np":1,"cix":2,"bm":0,"ix":3,"mn":"ADBE Vector Group","hd":false},{"ty":"gr","it":[{"ty":"rc","d":1,"s":{"a":0,"k":[41.63,41.63],"ix":2},"p":{"a":0,"k":[-1595.865,-118.189],"ix":3},"r":{"a":0,"k":0,"ix":4},"nm":"Rectangle Path 1","mn":"ADBE Vector Shape - Rect","hd":false},{"ty":"tr","p":{"a":0,"k":[0,0],"ix":2},"a":{"a":0,"k":[0,0],"ix":1},"s":{"a":0,"k":[100,100],"ix":3},"r":{"a":0,"k":0,"ix":6},"o":{"a":0,"k":100,"ix":7},"sk":{"a":0,"k":0,"ix":4},"sa":{"a":0,"k":0,"ix":5},"nm":"Transform"}],"nm":"Group 6","np":1,"cix":2,"bm":0,"ix":4,"mn":"ADBE Vector Group","hd":false},{"ty":"gr","it":[{"ty":"rc","d":1,"s":{"a":0,"k":[41.63,41.63],"ix":2},"p":{"a":0,"k":[-1595.865,-185.255],"ix":3},"r":{"a":0,"k":0,"ix":4},"nm":"Rectangle Path 1","mn":"ADBE Vector Shape - Rect","hd":false},{"ty":"tr","p":{"a":0,"k":[0,0],"ix":2},"a":{"a":0,"k":[0,0],"ix":1},"s":{"a":0,"k":[100,100],"ix":3},"r":{"a":0,"k":0,"ix":6},"o":{"a":0,"k":100,"ix":7},"sk":{"a":0,"k":0,"ix":4},"sa":{"a":0,"k":0,"ix":5},"nm":"Transform"}],"nm":"Group 7","np":1,"cix":2,"bm":0,"ix":5,"mn":"ADBE Vector Group","hd":false},{"ty":"gr","it":[{"ty":"rc","d":1,"s":{"a":0,"k":[41.63,41.63],"ix":2},"p":{"a":0,"k":[-1595.865,-252.321],"ix":3},"r":{"a":0,"k":0,"ix":4},"nm":"Rectangle Path 1","mn":"ADBE Vector Shape - Rect","hd":false},{"ty":"tr","p":{"a":0,"k":[0,0],"ix":2},"a":{"a":0,"k":[0,0],"ix":1},"s":{"a":0,"k":[100,100],"ix":3},"r":{"a":0,"k":0,"ix":6},"o":{"a":0,"k":100,"ix":7},"sk":{"a":0,"k":0,"ix":4},"sa":{"a":0,"k":0,"ix":5},"nm":"Transform"}],"nm":"Group 8","np":1,"cix":2,"bm":0,"ix":6,"mn":"ADBE Vector Group","hd":false},{"ty":"gr","it":[{"ty":"rc","d":3,"s":{"a":0,"k":[41.63,41.63],"ix":2},"p":{"a":0,"k":[-1664.902,-118.189],"ix":3},"r":{"a":0,"k":0,"ix":4},"nm":"Rectangle Path 1","mn":"ADBE Vector Shape - Rect","hd":false},{"ty":"tr","p":{"a":0,"k":[0,0],"ix":2},"a":{"a":0,"k":[0,0],"ix":1},"s":{"a":0,"k":[100,100],"ix":3},"r":{"a":0,"k":0,"ix":6},"o":{"a":0,"k":100,"ix":7},"sk":{"a":0,"k":0,"ix":4},"sa":{"a":0,"k":0,"ix":5},"nm":"Transform"}],"nm":"Group 9","np":1,"cix":2,"bm":0,"ix":7,"mn":"ADBE Vector Group","hd":false},{"ty":"gr","it":[{"ty":"rc","d":1,"s":{"a":0,"k":[41.63,41.63],"ix":2},"p":{"a":0,"k":[-1664.902,-252.321],"ix":3},"r":{"a":0,"k":0,"ix":4},"nm":"Rectangle Path 1","mn":"ADBE Vector Shape - Rect","hd":false},{"ty":"tr","p":{"a":0,"k":[0,0],"ix":2},"a":{"a":0,"k":[0,0],"ix":1},"s":{"a":0,"k":[100,100],"ix":3},"r":{"a":0,"k":0,"ix":6},"o":{"a":0,"k":100,"ix":7},"sk":{"a":0,"k":0,"ix":4},"sa":{"a":0,"k":0,"ix":5},"nm":"Transform"}],"nm":"Group 11","np":1,"cix":2,"bm":0,"ix":8,"mn":"ADBE Vector Group","hd":false},{"ty":"gr","it":[{"ty":"rc","d":3,"s":{"a":0,"k":[41.63,41.63],"ix":2},"p":{"a":0,"k":[-1733.938,-118.189],"ix":3},"r":{"a":0,"k":0,"ix":4},"nm":"Rectangle Path 1","mn":"ADBE Vector Shape - Rect","hd":false},{"ty":"tr","p":{"a":0,"k":[0,0],"ix":2},"a":{"a":0,"k":[0,0],"ix":1},"s":{"a":0,"k":[100,100],"ix":3},"r":{"a":0,"k":0,"ix":6},"o":{"a":0,"k":100,"ix":7},"sk":{"a":0,"k":0,"ix":4},"sa":{"a":0,"k":0,"ix":5},"nm":"Transform"}],"nm":"Group 12","np":1,"cix":2,"bm":0,"ix":9,"mn":"ADBE Vector Group","hd":false},{"ty":"gr","it":[{"ty":"rc","d":3,"s":{"a":0,"k":[41.63,41.63],"ix":2},"p":{"a":0,"k":[-1733.938,-185.255],"ix":3},"r":{"a":0,"k":0,"ix":4},"nm":"Rectangle Path 1","mn":"ADBE Vector Shape - Rect","hd":false},{"ty":"tr","p":{"a":0,"k":[0,0],"ix":2},"a":{"a":0,"k":[0,0],"ix":1},"s":{"a":0,"k":[100,100],"ix":3},"r":{"a":0,"k":0,"ix":6},"o":{"a":0,"k":100,"ix":7},"sk":{"a":0,"k":0,"ix":4},"sa":{"a":0,"k":0,"ix":5},"nm":"Transform"}],"nm":"Group 13","np":1,"cix":2,"bm":0,"ix":10,"mn":"ADBE Vector Group","hd":false},{"ty":"gr","it":[{"ty":"rc","d":1,"s":{"a":0,"k":[41.63,41.63],"ix":2},"p":{"a":0,"k":[-1733.938,-252.321],"ix":3},"r":{"a":0,"k":0,"ix":4},"nm":"Rectangle Path 1","mn":"ADBE Vector Shape - Rect","hd":false},{"ty":"tr","p":{"a":0,"k":[0,0],"ix":2},"a":{"a":0,"k":[0,0],"ix":1},"s":{"a":0,"k":[100,100],"ix":3},"r":{"a":0,"k":0,"ix":6},"o":{"a":0,"k":100,"ix":7},"sk":{"a":0,"k":0,"ix":4},"sa":{"a":0,"k":0,"ix":5},"nm":"Transform"}],"nm":"Group 14","np":1,"cix":2,"bm":0,"ix":11,"mn":"ADBE Vector Group","hd":false},{"ty":"gr","it":[{"ty":"rc","d":1,"s":{"a":0,"k":[41.63,41.63],"ix":2},"p":{"a":0,"k":[-1802.974,-118.189],"ix":3},"r":{"a":0,"k":0,"ix":4},"nm":"Rectangle Path 1","mn":"ADBE Vector Shape - Rect","hd":false},{"ty":"tr","p":{"a":0,"k":[0,0],"ix":2},"a":{"a":0,"k":[0,0],"ix":1},"s":{"a":0,"k":[100,100],"ix":3},"r":{"a":0,"k":0,"ix":6},"o":{"a":0,"k":100,"ix":7},"sk":{"a":0,"k":0,"ix":4},"sa":{"a":0,"k":0,"ix":5},"nm":"Transform"}],"nm":"Group 15","np":1,"cix":2,"bm":0,"ix":12,"mn":"ADBE Vector Group","hd":false},{"ty":"gr","it":[{"ty":"rc","d":1,"s":{"a":0,"k":[41.63,41.63],"ix":2},"p":{"a":0,"k":[-1802.974,-185.255],"ix":3},"r":{"a":0,"k":0,"ix":4},"nm":"Rectangle Path 1","mn":"ADBE Vector Shape - Rect","hd":false},{"ty":"tr","p":{"a":0,"k":[0,0],"ix":2},"a":{"a":0,"k":[0,0],"ix":1},"s":{"a":0,"k":[100,100],"ix":3},"r":{"a":0,"k":0,"ix":6},"o":{"a":0,"k":100,"ix":7},"sk":{"a":0,"k":0,"ix":4},"sa":{"a":0,"k":0,"ix":5},"nm":"Transform"}],"nm":"Group 16","np":1,"cix":2,"bm":0,"ix":13,"mn":"ADBE Vector Group","hd":false},{"ty":"rd","nm":"Round Corners 1","r":{"a":0,"k":10,"ix":1},"ix":14,"mn":"ADBE Vector Filter - RC","hd":false},{"ty":"st","c":{"a":0,"k":[0.12158203125,0.117645263672,0.172546386719,1],"ix":3},"o":{"a":0,"k":100,"ix":4},"w":{"a":0,"k":5,"ix":5},"lc":1,"lj":1,"ml":4,"bm":0,"nm":"Stroke 1","mn":"ADBE Vector Graphic - Stroke","hd":false},{"ty":"gr","it":[{"ind":0,"ty":"sh","ix":1,"ks":{"a":0,"k":{"i":[[-6.605,1.985],[-0.661,29.111],[0,0],[-33.027,4.631],[0,0],[1.245,11.946],[-9.248,13.232],[-2.642,-23.818],[1.321,-3.308],[2.642,8.601],[-2.579,2.454],[-3.303,-1.323],[-5.284,1.323],[-3.303,1.323],[-3.963,-17.864],[4.624,-3.97],[15.853,4.632],[-9.908,-0.662],[0.648,3.244],[-3.963,0],[-4.624,-27.788],[-0.661,-7.278],[44.917,-10.586],[8.587,1.323],[12.159,15.038],[19.156,-3.308]],"o":[[6.605,-1.985],[0.661,-29.111],[0,0],[5.924,-0.831],[0,0],[-0.935,-8.975],[9.248,-13.232],[2.642,23.818],[-1.321,3.308],[-2.642,-8.601],[26.422,-25.142],[9.382,3.759],[5.284,-1.323],[3.303,-1.323],[6.295,28.374],[-4.624,3.97],[-15.853,-4.632],[5.313,0.355],[-0.661,-3.308],[3.963,0],[4.624,27.788],[0.661,7.278],[-44.917,10.586],[-3.783,-0.583],[-15.441,-19.097],[-9.137,1.578]],"v":[[-1908.428,-108.153],[-1857.566,-146.527],[-1861.53,-300.686],[-1839.071,-352.954],[-1809.346,-353.616],[-1806.429,-377.722],[-1804.062,-397.283],[-1770.374,-391.99],[-1769.053,-307.302],[-1794.814,-303.332],[-1794.154,-382.727],[-1761.787,-352.954],[-1578.816,-363.54],[-1565.605,-393.313],[-1531.256,-391.99],[-1542.485,-311.272],[-1553.715,-309.287],[-1551.073,-385.374],[-1529.935,-381.404],[-1518.706,-362.217],[-1477.091,-337.075],[-1470.486,-75.733],[-1526.632,-30.081],[-1798.778,-34.051],[-1845.095,-51.315],[-1869.456,-103.522]],"c":false},"ix":2},"nm":"Path 1","mn":"ADBE Vector Shape - Group","hd":false},{"ty":"st","c":{"a":0,"k":[0.12158203125,0.117645263672,0.172546386719,1],"ix":3},"o":{"a":0,"k":100,"ix":4},"w":{"a":0,"k":5,"ix":5},"lc":1,"lj":1,"ml":4,"bm":0,"nm":"Stroke 1","mn":"ADBE Vector Graphic - Stroke","hd":false},{"ty":"tr","p":{"a":0,"k":[0,0],"ix":2},"a":{"a":0,"k":[0,0],"ix":1},"s":{"a":0,"k":[100,100],"ix":3},"r":{"a":0,"k":0,"ix":6},"o":{"a":0,"k":100,"ix":7},"sk":{"a":0,"k":0,"ix":4},"sa":{"a":0,"k":0,"ix":5},"nm":"Transform"}],"nm":"Shape 1","np":3,"cix":2,"bm":0,"ix":17,"mn":"ADBE Vector Group","hd":false}],"ip":0,"op":136.000005539394,"st":0,"bm":0}],"markers":[]}